admin_ui/__init__.py
admin_ui/apps.py
admin_ui/compat.py
admin_ui/locale/bg/LC_MESSAGES/django.mo
admin_ui/locale/bg/LC_MESSAGES/django.po
admin_ui/locale/de/LC_MESSAGES/django.mo
admin_ui/locale/de/LC_MESSAGES/django.po
admin_ui/locale/es/LC_MESSAGES/django.mo
admin_ui/locale/es/LC_MESSAGES/django.po
admin_ui/locale/fr/LC_MESSAGES/django.mo
admin_ui/locale/fr/LC_MESSAGES/django.po
admin_ui/locale/hu/LC_MESSAGES/django.mo
admin_ui/locale/hu/LC_MESSAGES/django.po
admin_ui/locale/ru/LC_MESSAGES/django.mo
admin_ui/locale/ru/LC_MESSAGES/django.po
admin_ui/locale/zh_Hans/LC_MESSAGES/django.mo
admin_ui/locale/zh_Hans/LC_MESSAGES/django.po
admin_ui/locale/zh_Hant/LC_MESSAGES/django.mo
admin_ui/locale/zh_Hant/LC_MESSAGES/django.po
admin_ui/settings.py
admin_ui/static/admin/js/cancel.js
admin_ui/static/admin/js/popup_response.js
admin_ui/static/admin_ui/css/main.css
admin_ui/static/admin_ui/img/calendar-icons.svg
admin_ui/static/admin_ui/img/default-log.svg
admin_ui/static/admin_ui/img/default.jpg
admin_ui/static/admin_ui/img/icon-calendar.svg
admin_ui/static/admin_ui/img/icon-changelink.svg
admin_ui/static/admin_ui/img/selector-icons.svg
admin_ui/static/admin_ui/js/change_form.js
admin_ui/static/admin_ui/js/change_list.js
admin_ui/static/admin_ui/js/main.js
admin_ui/static/admin_ui/js/related-modal.js
admin_ui/static/admin_ui/js/ui-builder.js
admin_ui/static/admin_ui/plugins/bootstrap-show-modal/bootstrap-show-modal.min.js
admin_ui/static/vendor/adminlte/css/adminlte.min.css
admin_ui/static/vendor/adminlte/css/adminlte.min.css.map
admin_ui/static/vendor/adminlte/img/AdminLTELogo.png
admin_ui/static/vendor/adminlte/img/icons.png
admin_ui/static/vendor/adminlte/img/user2-160x160.jpg
admin_ui/static/vendor/adminlte/js/adminlte.min.js
admin_ui/static/vendor/adminlte/js/adminlte.min.js.map
admin_ui/static/vendor/bootstrap/js/bootstrap.min.js
admin_ui/static/vendor/bootstrap/js/bootstrap.min.js.map
admin_ui/static/vendor/bootswatch/cerulean/bootstrap.min.css
django_admin_ui-1.0.1.dist-info/WHEEL
django_admin_ui-1.0.1.dist-info/METADATA
django_admin_ui-1.0.1.dist-info/LICENSE
django_admin_ui-1.0.1.dist-info/RECORD
