Metadata-Version: 2.1
Name: django-admin-ui
Version: 1.0.1
Summary: This is just a fork from the official django-jazzmin repository, i only changed all occurrences of jazzmin to admin_ui and few tweaks within the static directory. all credits goes to the original author (farridav)
Home-page: https://github.com/digglepress/django-admin-ui
License: MIT
Keywords: django,dashboard,theme,admin,ui
Author: Victor Bekee
Maintainer: Victor Bekee
Maintainer-email: youngtech412@gmail.com
Requires-Python: >=3.6.2
Classifier: Development Status :: 4 - Beta
Classifier: Environment :: Web Environment
Classifier: Framework :: Django
Classifier: Framework :: Django :: 2.2
Classifier: Framework :: Django :: 3.0
Classifier: Framework :: Django :: 3.1
Classifier: License :: OSI Approved :: MIT License
Classifier: Operating System :: OS Independent
Classifier: Programming Language :: Python
Classifier: Programming Language :: Python :: 3
Classifier: Programming Language :: Python :: 3.7
Classifier: Programming Language :: Python :: 3.8
Classifier: Programming Language :: Python :: 3.9
Classifier: Programming Language :: Python :: 3.10
Classifier: Programming Language :: Python :: 3.11
Classifier: Programming Language :: Python :: 3
Classifier: Programming Language :: Python :: 3 :: Only
Classifier: Programming Language :: Python :: 3.10
Classifier: Programming Language :: Python :: 3.6
Classifier: Programming Language :: Python :: 3.7
Classifier: Programming Language :: Python :: 3.8
Classifier: Programming Language :: Python :: 3.9
Classifier: Topic :: Internet :: WWW/HTTP
Classifier: Topic :: Internet :: WWW/HTTP :: Dynamic Content
Classifier: Topic :: Internet :: WWW/HTTP :: WSGI
Classifier: Topic :: Software Development :: Libraries :: Python Modules
Requires-Dist: dj-database-url (>=1.2.0,<2.0.0)
Requires-Dist: django (>=2.2)
Requires-Dist: factory-boy (>=3.2.1,<4.0.0)
Requires-Dist: gunicorn (>=20.1.0,<21.0.0)
Requires-Dist: pluggy (>=1.0.0,<2.0.0)
Requires-Dist: psycopg2-binary (>=2.9.5,<3.0.0)
Project-URL: All Releases, https://github.com/digglepress/django-admin-ui/releases
Project-URL: Bug Tracker, https://github.com/digglepress/django-admin-ui/issues
Project-URL: Documentation, https://django-jazzmin.readthedocs.io
Project-URL: Latest Release, https://github.com/digglepress/django-admin-ui/releases/latest
Project-URL: Repository, https://github.com/digglepress/django-admin-ui
Project-URL: Source, https://github.com/digglepress/django-admin-ui
